openfisca_mali/__init__.py
openfisca_mali/entities.py
openfisca_mali/input_data_builder.py
openfisca_mali/survey_scenarios.py
openfisca_mali/assets/.gitkeep
openfisca_mali/assets/definition_variables_micro_MLI.xlsx
openfisca_mali/assets/recettes_fiscales_MLI.xlsx
openfisca_mali/parameters/__init__.py
openfisca_mali/parameters/prelevements_obligatoires/impots_directs/impot_traitement_salaire.yaml
openfisca_mali/parameters/prelevements_obligatoires/impots_indirects/index.yaml
openfisca_mali/parameters/prelevements_obligatoires/impots_indirects/iscp.yaml
openfisca_mali/parameters/prelevements_obligatoires/impots_indirects/tva.yaml
openfisca_mali/parameters/reductions_pour_charge_de_famille/limite_nombre_enfants.yaml
openfisca_mali/parameters/reductions_pour_charge_de_famille/repartition_parents.yaml
openfisca_mali/parameters/reductions_pour_charge_de_famille/taux_couple.yaml
openfisca_mali/parameters/reductions_pour_charge_de_famille/taux_enfant_a_charge.yaml
openfisca_mali/parameters/reductions_pour_charge_de_famille/taux_seul.yaml
openfisca_mali/reforms/__init__.py
openfisca_mali/tests/__init__.py
openfisca_mali/tests/test_survey_scenario_from_stata_data.py
openfisca_mali/tests/data/__init__.py
openfisca_mali/tests/data/fake_data_generator.py
openfisca_mali/tests/data/household.dta
openfisca_mali/tests/data/person.dta
openfisca_mali/tests/formulas/impot_traitement_salaire.yaml
openfisca_mali/variables/__init__.py
openfisca_mali/variables/caracteristiques_socio_demographiques.py
openfisca_mali/variables/consommation.py
openfisca_mali/variables/prestations.py
openfisca_mali/variables/revenus.py
openfisca_mali/variables/weights.py
openfisca_mali/variables/prelevements_obligatoires/__init__.py
openfisca_mali/variables/prelevements_obligatoires/impots_directs.py
openfisca_mali/variables/prelevements_obligatoires/impots_indirects.py
openfisca_mali/variables/prelevements_obligatoires/prelevements_sociaux.py
OpenFisca_Mali-1.2.0.dist-info/LICENSE
OpenFisca_Mali-1.2.0.dist-info/METADATA
OpenFisca_Mali-1.2.0.dist-info/WHEEL
OpenFisca_Mali-1.2.0.dist-info/top_level.txt
OpenFisca_Mali-1.2.0.dist-info/RECORD
