Metadata-Version: 2.1
Name: OpenFisca-Mali
Version: 1.2.0
Summary: OpenFisca tax and benefit system for Mali
Home-page: https://github.com/openfisca/openfisca-mali
Author: OpenFisca Team
Author-email: contact@openfisca.fr
License: http://www.fsf.org/licensing/licenses/agpl-3.0.html
Keywords: benefit microsimulation social tax
Platform: UNKNOWN
Requires-Dist: OpenFisca-Core (<35.0,>=34.2.2)
Provides-Extra: ceq
Requires-Dist: openfisca-ceq (>=0.4.0) ; extra == 'ceq'
Provides-Extra: dev
Requires-Dist: autopep8 (==1.5) ; extra == 'dev'
Requires-Dist: flake8 (<3.8.0,>=3.5.0) ; extra == 'dev'
Requires-Dist: flake8-print ; extra == 'dev'
Requires-Dist: pycodestyle (<2.6.0,>=2.3.0) ; extra == 'dev'
Requires-Dist: pytest (<6.0) ; extra == 'dev'
Requires-Dist: scipy (>=0.17) ; extra == 'dev'
Requires-Dist: requests (>=2.8) ; extra == 'dev'
Requires-Dist: openfisca-ceq (>=0.4.0) ; extra == 'dev'
Requires-Dist: openfisca-survey-manager[dev] (<1.0,>=0.38) ; extra == 'dev'
Requires-Dist: yamllint (<1.21,>=1.11.1) ; extra == 'dev'
